{
  "code": "160632",
  "days": 370,
  "update_time": "2026-05-14 16:22:24",
  "history": [
    {
      "date": "2026-05-14",
      "nav": "",
      "valuation": 0.291,
      "price": 0.29,
      "change": 0.0,
      "premium": ""
    },
    {
      "date": "2026-05-13",
      "nav": 0.2892,
      "valuation": 0.291,
      "price": 0.29,
      "change": -1.02,
      "premium": 0.28
    },
    {
      "date": "2026-05-12",
      "nav": 0.2928,
      "valuation": 0.291,
      "price": 0.293,
      "change": -1.68,
      "premium": 0.07
    },
    {
      "date": "2026-05-11",
      "nav": 0.297,
      "valuation": 0.291,
      "price": 0.298,
      "change": 0.0,
      "premium": 0.34
    },
    {
      "date": "2026-05-08",
      "nav": 0.2974,
      "valuation": 0.291,
      "price": 0.298,
      "change": 0.0,
      "premium": 0.2
    },
    {
      "date": "2026-05-08",
      "nav": 0.2974,
      "valuation": 0.2974,
      "price": 0.298,
      "change": 0.0,
      "premium": 0.2
    },
    {
      "date": "2026-05-07",
      "nav": 0.2985,
      "valuation": 0.291,
      "price": 0.298,
      "change": -0.33,
      "premium": -0.17
    },
    {
      "date": "2026-05-06",
      "nav": 0.2978,
      "valuation": 0.2974,
      "price": 0.299,
      "change": -0.66,
      "premium": 0.4
    },
    {
      "date": "2026-04-30",
      "nav": 0.3023,
      "valuation": 0.2974,
      "price": 0.301,
      "change": -0.66,
      "premium": -0.43
    },
    {
      "date": "2026-04-29",
      "nav": 0.3045,
      "valuation": 0.2974,
      "price": 0.303,
      "change": 0.66,
      "premium": -0.49
    },
    {
      "date": "2026-04-28",
      "nav": 0.3013,
      "valuation": 0.2974,
      "price": 0.301,
      "change": -0.33,
      "premium": -0.1
    },
    {
      "date": "2026-04-27",
      "nav": 0.301,
      "valuation": 0.2974,
      "price": 0.302,
      "change": -1.31,
      "premium": 0.33
    },
    {
      "date": "2026-04-24",
      "nav": 0.3065,
      "valuation": 0.2974,
      "price": 0.306,
      "change": 0.33,
      "premium": -0.16
    },
    {
      "date": "2026-04-23",
      "nav": 0.3056,
      "valuation": 0.2974,
      "price": 0.305,
      "change": 0.99,
      "premium": -0.2
    },
    {
      "date": "2026-04-22",
      "nav": 0.3006,
      "valuation": 0.2974,
      "price": 0.302,
      "change": -0.33,
      "premium": 0.47
    },
    {
      "date": "2026-04-21",
      "nav": 0.3011,
      "valuation": 0.2974,
      "price": 0.303,
      "change": 0.0,
      "premium": 0.63
    },
    {
      "date": "2026-04-20",
      "nav": 0.3024,
      "valuation": 0.2974,
      "price": 0.303,
      "change": 0.0,
      "premium": 0.2
    },
    {
      "date": "2026-04-17",
      "nav": 0.3026,
      "valuation": 0.2974,
      "price": 0.303,
      "change": -1.62,
      "premium": 0.13
    },
    {
      "date": "2026-04-16",
      "nav": 0.3078,
      "valuation": 0.2974,
      "price": 0.308,
      "change": 0.33,
      "premium": 0.06
    },
    {
      "date": "2026-04-15",
      "nav": 0.3073,
      "valuation": 0.2974,
      "price": 0.307,
      "change": 0.66,
      "premium": -0.1
    },
    {
      "date": "2026-04-14",
      "nav": 0.3063,
      "valuation": 0.2974,
      "price": 0.305,
      "change": 0.0,
      "premium": -0.42
    },
    {
      "date": "2026-04-13",
      "nav": 0.3048,
      "valuation": 0.2974,
      "price": 0.305,
      "change": -0.33,
      "premium": 0.07
    },
    {
      "date": "2026-04-10",
      "nav": 0.3063,
      "valuation": 0.2974,
      "price": 0.306,
      "change": 0.33,
      "premium": -0.1
    },
    {
      "date": "2026-04-09",
      "nav": 0.3059,
      "valuation": 0.2974,
      "price": 0.305,
      "change": -1.61,
      "premium": -0.29
    },
    {
      "date": "2026-04-08",
      "nav": 0.311,
      "valuation": 0.2974,
      "price": 0.31,
      "change": 1.64,
      "premium": -0.32
    },
    {
      "date": "2026-04-07",
      "nav": 0.3064,
      "valuation": 0.2974,
      "price": 0.305,
      "change": -0.65,
      "premium": -0.46
    },
    {
      "date": "2026-04-03",
      "nav": 0.3076,
      "valuation": 0.2974,
      "price": 0.307,
      "change": -0.97,
      "premium": -0.2
    },
    {
      "date": "2026-04-02",
      "nav": 0.3118,
      "valuation": 0.2974,
      "price": 0.31,
      "change": -0.32,
      "premium": -0.58
    },
    {
      "date": "2026-04-01",
      "nav": 0.3108,
      "valuation": 0.2974,
      "price": 0.311,
      "change": 0.97,
      "premium": 0.06
    },
    {
      "date": "2026-03-31",
      "nav": 0.3069,
      "valuation": 0.2974,
      "price": 0.308,
      "change": 0.33,
      "premium": 0.36
    },
    {
      "date": "2026-03-30",
      "nav": 0.3078,
      "valuation": 0.2974,
      "price": 0.307,
      "change": 0.33,
      "premium": -0.26
    },
    {
      "date": "2026-03-27",
      "nav": 0.3069,
      "valuation": 0.2974,
      "price": 0.306,
      "change": 0.99,
      "premium": -0.29
    },
    {
      "date": "2026-03-26",
      "nav": 0.3032,
      "valuation": 0.2974,
      "price": 0.303,
      "change": -1.3,
      "premium": -0.07
    },
    {
      "date": "2026-03-25",
      "nav": 0.3072,
      "valuation": 0.2974,
      "price": 0.307,
      "change": 0.33,
      "premium": -0.07
    },
    {
      "date": "2026-03-24",
      "nav": 0.3054,
      "valuation": 0.2974,
      "price": 0.306,
      "change": 1.32,
      "premium": 0.2
    },
    {
      "date": "2026-03-23",
      "nav": 0.302,
      "valuation": 0.2974,
      "price": 0.302,
      "change": -3.21,
      "premium": ""
    },
    {
      "date": "2026-03-20",
      "nav": 0.3119,
      "valuation": 0.2974,
      "price": 0.312,
      "change": -0.64,
      "premium": 0.03
    },
    {
      "date": "2026-03-19",
      "nav": 0.3144,
      "valuation": 0.2974,
      "price": 0.314,
      "change": -1.57,
      "premium": -0.13
    },
    {
      "date": "2026-03-18",
      "nav": 0.3191,
      "valuation": 0.2974,
      "price": 0.319,
      "change": -0.62,
      "premium": -0.03
    },
    {
      "date": "2026-03-17",
      "nav": 0.3227,
      "valuation": 0.2974,
      "price": 0.321,
      "change": 0.0,
      "premium": -0.53
    },
    {
      "date": "2026-03-16",
      "nav": 0.3229,
      "valuation": 0.2974,
      "price": 0.321,
      "change": 0.94,
      "premium": -0.59
    },
    {
      "date": "2026-03-13",
      "nav": 0.3187,
      "valuation": 0.2974,
      "price": 0.318,
      "change": 0.95,
      "premium": -0.22
    },
    {
      "date": "2026-03-12",
      "nav": 0.3154,
      "valuation": 0.2974,
      "price": 0.315,
      "change": 0.0,
      "premium": -0.13
    },
    {
      "date": "2026-03-11",
      "nav": 0.3156,
      "valuation": 0.2974,
      "price": 0.315,
      "change": -0.32,
      "premium": -0.19
    },
    {
      "date": "2026-03-10",
      "nav": 0.3159,
      "valuation": 0.2974,
      "price": 0.316,
      "change": 0.32,
      "premium": 0.03
    },
    {
      "date": "2026-03-09",
      "nav": 0.3149,
      "valuation": 0.2974,
      "price": 0.315,
      "change": -0.94,
      "premium": 0.03
    },
    {
      "date": "2026-03-06",
      "nav": 0.3177,
      "valuation": 0.2974,
      "price": 0.318,
      "change": 1.6,
      "premium": 0.09
    },
    {
      "date": "2026-03-05",
      "nav": 0.3132,
      "valuation": 0.2974,
      "price": 0.313,
      "change": 0.0,
      "premium": -0.06
    },
    {
      "date": "2026-03-04",
      "nav": 0.313,
      "valuation": 0.2974,
      "price": 0.313,
      "change": -2.19,
      "premium": ""
    },
    {
      "date": "2026-03-03",
      "nav": 0.3202,
      "valuation": 0.2974,
      "price": 0.32,
      "change": -0.31,
      "premium": -0.06
    },
    {
      "date": "2026-03-02",
      "nav": 0.3207,
      "valuation": 0.2974,
      "price": 0.321,
      "change": -1.53,
      "premium": 0.09
    },
    {
      "date": "2026-02-27",
      "nav": 0.3265,
      "valuation": 0.2974,
      "price": 0.326,
      "change": 0.0,
      "premium": -0.15
    },
    {
      "date": "2026-02-26",
      "nav": 0.3267,
      "valuation": 0.2974,
      "price": 0.326,
      "change": -1.21,
      "premium": -0.21
    },
    {
      "date": "2026-02-25",
      "nav": 0.331,
      "valuation": 0.2974,
      "price": 0.33,
      "change": 0.3,
      "premium": -0.3
    },
    {
      "date": "2026-02-24",
      "nav": 0.3291,
      "valuation": 0.2974,
      "price": 0.329,
      "change": -0.9,
      "premium": -0.03
    },
    {
      "date": "2026-02-13",
      "nav": 0.3329,
      "valuation": 0.2974,
      "price": 0.332,
      "change": -0.3,
      "premium": -0.27
    },
    {
      "date": "2026-02-12",
      "nav": 0.3332,
      "valuation": 0.2974,
      "price": 0.333,
      "change": -1.19,
      "premium": -0.06
    },
    {
      "date": "2026-02-11",
      "nav": 0.3384,
      "valuation": 0.2974,
      "price": 0.337,
      "change": 0.0,
      "premium": -0.41
    },
    {
      "date": "2026-02-10",
      "nav": 0.339,
      "valuation": 0.2974,
      "price": 0.337,
      "change": -1.75,
      "premium": -0.59
    },
    {
      "date": "2026-02-09",
      "nav": 0.3442,
      "valuation": 0.2974,
      "price": 0.343,
      "change": 0.29,
      "premium": -0.35
    },
    {
      "date": "2026-02-06",
      "nav": 0.344,
      "valuation": 0.2974,
      "price": 0.342,
      "change": -2.01,
      "premium": -0.58
    },
    {
      "date": "2026-02-05",
      "nav": 0.3513,
      "valuation": 0.2974,
      "price": 0.349,
      "change": 0.29,
      "premium": -0.65
    },
    {
      "date": "2026-02-04",
      "nav": 0.3495,
      "valuation": 0.2974,
      "price": 0.348,
      "change": 2.05,
      "premium": -0.43
    },
    {
      "date": "2026-02-03",
      "nav": 0.3426,
      "valuation": 0.2974,
      "price": 0.341,
      "change": 0.29,
      "premium": -0.47
    },
    {
      "date": "2026-02-02",
      "nav": 0.3413,
      "valuation": 0.2974,
      "price": 0.34,
      "change": 1.49,
      "premium": -0.38
    },
    {
      "date": "2026-01-30",
      "nav": 0.3358,
      "valuation": 0.2974,
      "price": 0.335,
      "change": -5.1,
      "premium": -0.24
    },
    {
      "date": "2026-01-29",
      "nav": 0.3487,
      "valuation": 0.2974,
      "price": 0.353,
      "change": 9.97,
      "premium": 1.23
    },
    {
      "date": "2026-01-28",
      "nav": 0.3213,
      "valuation": 0.2974,
      "price": 0.321,
      "change": -0.31,
      "premium": -0.09
    },
    {
      "date": "2026-01-27",
      "nav": 0.3212,
      "valuation": 0.2974,
      "price": 0.322,
      "change": -1.23,
      "premium": 0.25
    },
    {
      "date": "2026-01-26",
      "nav": 0.3253,
      "valuation": 0.2974,
      "price": 0.326,
      "change": -0.91,
      "premium": 0.22
    },
    {
      "date": "2026-01-23",
      "nav": 0.3282,
      "valuation": 0.2974,
      "price": 0.329,
      "change": -0.3,
      "premium": 0.24
    },
    {
      "date": "2026-01-22",
      "nav": 0.3288,
      "valuation": 0.2974,
      "price": 0.33,
      "change": 0.0,
      "premium": 0.36
    },
    {
      "date": "2026-01-21",
      "nav": 0.3297,
      "valuation": 0.2974,
      "price": 0.33,
      "change": -1.49,
      "premium": 0.09
    },
    {
      "date": "2026-01-20",
      "nav": 0.3357,
      "valuation": 0.2974,
      "price": 0.335,
      "change": 0.0,
      "premium": -0.21
    },
    {
      "date": "2026-01-19",
      "nav": 0.3331,
      "valuation": 0.2974,
      "price": 0.335,
      "change": -0.3,
      "premium": 0.57
    },
    {
      "date": "2026-01-16",
      "nav": 0.3336,
      "valuation": 0.2974,
      "price": 0.336,
      "change": -0.3,
      "premium": 0.72
    },
    {
      "date": "2026-01-15",
      "nav": 0.3359,
      "valuation": 0.2974,
      "price": 0.337,
      "change": -0.59,
      "premium": 0.33
    },
    {
      "date": "2026-01-14",
      "nav": 0.3388,
      "valuation": 0.2974,
      "price": 0.339,
      "change": -0.88,
      "premium": 0.06
    },
    {
      "date": "2026-01-13",
      "nav": 0.3409,
      "valuation": 0.2974,
      "price": 0.342,
      "change": -0.29,
      "premium": 0.32
    },
    {
      "date": "2026-01-12",
      "nav": 0.3442,
      "valuation": 0.2974,
      "price": 0.343,
      "change": 0.59,
      "premium": -0.35
    },
    {
      "date": "2026-01-09",
      "nav": 0.3403,
      "valuation": 0.2974,
      "price": 0.341,
      "change": 0.29,
      "premium": 0.21
    },
    {
      "date": "2026-01-08",
      "nav": 0.3391,
      "valuation": 0.2974,
      "price": 0.34,
      "change": 0.0,
      "premium": 0.27
    },
    {
      "date": "2026-01-07",
      "nav": 0.3403,
      "valuation": 0.2974,
      "price": 0.34,
      "change": -0.29,
      "premium": -0.09
    },
    {
      "date": "2026-01-06",
      "nav": 0.342,
      "valuation": 0.2974,
      "price": 0.341,
      "change": 0.59,
      "premium": -0.29
    },
    {
      "date": "2026-01-05",
      "nav": 0.3397,
      "valuation": 0.2974,
      "price": 0.339,
      "change": 0.89,
      "premium": -0.21
    },
    {
      "date": "2025-12-31",
      "nav": 0.3336,
      "valuation": 0.2974,
      "price": 0.336,
      "change": -0.88,
      "premium": 0.72
    },
    {
      "date": "2025-12-30",
      "nav": 0.3364,
      "valuation": 0.2974,
      "price": 0.339,
      "change": -0.29,
      "premium": 0.77
    },
    {
      "date": "2025-12-29",
      "nav": 0.338,
      "valuation": 0.2974,
      "price": 0.34,
      "change": -0.58,
      "premium": 0.59
    },
    {
      "date": "2025-12-26",
      "nav": 0.3421,
      "valuation": 0.2974,
      "price": 0.342,
      "change": -0.58,
      "premium": -0.03
    },
    {
      "date": "2025-12-25",
      "nav": 0.3445,
      "valuation": 0.2974,
      "price": 0.344,
      "change": 0.58,
      "premium": -0.15
    },
    {
      "date": "2025-12-24",
      "nav": 0.3407,
      "valuation": 0.2974,
      "price": 0.342,
      "change": 0.0,
      "premium": 0.38
    },
    {
      "date": "2025-12-23",
      "nav": 0.3418,
      "valuation": 0.2974,
      "price": 0.342,
      "change": -0.58,
      "premium": 0.06
    },
    {
      "date": "2025-12-22",
      "nav": 0.3441,
      "valuation": 0.2974,
      "price": 0.344,
      "change": 0.0,
      "premium": -0.03
    },
    {
      "date": "2025-12-19",
      "nav": 0.3448,
      "valuation": 0.2974,
      "price": 0.344,
      "change": 0.29,
      "premium": -0.23
    },
    {
      "date": "2025-12-18",
      "nav": 0.3427,
      "valuation": 0.2974,
      "price": 0.343,
      "change": 0.0,
      "premium": 0.09
    },
    {
      "date": "2025-12-17",
      "nav": 0.3439,
      "valuation": 0.2974,
      "price": 0.343,
      "change": -0.29,
      "premium": -0.26
    },
    {
      "date": "2025-12-16",
      "nav": 0.3444,
      "valuation": 0.2974,
      "price": 0.344,
      "change": -0.29,
      "premium": -0.12
    },
    {
      "date": "2025-12-15",
      "nav": 0.3448,
      "valuation": 0.2974,
      "price": 0.345,
      "change": 0.58,
      "premium": 0.06
    },
    {
      "date": "2025-12-12",
      "nav": 0.3431,
      "valuation": 0.2974,
      "price": 0.343,
      "change": 0.59,
      "premium": -0.03
    },
    {
      "date": "2025-12-11",
      "nav": 0.3416,
      "valuation": 0.2974,
      "price": 0.341,
      "change": -0.87,
      "premium": -0.18
    },
    {
      "date": "2025-12-10",
      "nav": 0.3438,
      "valuation": 0.2974,
      "price": 0.344,
      "change": 0.29,
      "premium": 0.06
    },
    {
      "date": "2025-12-09",
      "nav": 0.3417,
      "valuation": 0.2974,
      "price": 0.343,
      "change": -1.15,
      "premium": 0.38
    },
    {
      "date": "2025-12-08",
      "nav": 0.3466,
      "valuation": 0.2974,
      "price": 0.347,
      "change": -1.14,
      "premium": 0.12
    },
    {
      "date": "2025-12-05",
      "nav": 0.35,
      "valuation": 0.2974,
      "price": 0.351,
      "change": 0.29,
      "premium": 0.29
    },
    {
      "date": "2025-12-04",
      "nav": 0.3485,
      "valuation": 0.2974,
      "price": 0.35,
      "change": -1.69,
      "premium": 0.43
    },
    {
      "date": "2025-12-03",
      "nav": 0.3545,
      "valuation": 0.2974,
      "price": 0.356,
      "change": -0.84,
      "premium": 0.42
    },
    {
      "date": "2025-12-02",
      "nav": 0.3585,
      "valuation": 0.2974,
      "price": 0.359,
      "change": -0.83,
      "premium": 0.14
    },
    {
      "date": "2025-12-01",
      "nav": 0.3619,
      "valuation": 0.2974,
      "price": 0.362,
      "change": 0.0,
      "premium": 0.03
    },
    {
      "date": "2025-11-28",
      "nav": 0.3619,
      "valuation": 0.2974,
      "price": 0.362,
      "change": 0.0,
      "premium": 0.03
    },
    {
      "date": "2025-11-27",
      "nav": 0.3617,
      "valuation": 0.2974,
      "price": 0.362,
      "change": 0.0,
      "premium": 0.08
    },
    {
      "date": "2025-11-26",
      "nav": 0.3614,
      "valuation": 0.2974,
      "price": 0.362,
      "change": 0.28,
      "premium": 0.17
    },
    {
      "date": "2025-11-25",
      "nav": 0.361,
      "valuation": 0.2974,
      "price": 0.361,
      "change": 0.0,
      "premium": ""
    },
    {
      "date": "2025-11-24",
      "nav": 0.3609,
      "valuation": 0.2974,
      "price": 0.361,
      "change": 0.0,
      "premium": 0.03
    },
    {
      "date": "2025-11-21",
      "nav": 0.3624,
      "valuation": 0.2974,
      "price": 0.361,
      "change": -1.37,
      "premium": -0.39
    },
    {
      "date": "2025-11-20",
      "nav": 0.3663,
      "valuation": 0.2974,
      "price": 0.366,
      "change": 0.27,
      "premium": -0.08
    },
    {
      "date": "2025-11-19",
      "nav": 0.367,
      "valuation": 0.2974,
      "price": 0.365,
      "change": -1.08,
      "premium": -0.54
    },
    {
      "date": "2025-11-18",
      "nav": 0.3699,
      "valuation": 0.2974,
      "price": 0.369,
      "change": -0.27,
      "premium": -0.24
    },
    {
      "date": "2025-11-17",
      "nav": 0.3712,
      "valuation": 0.2974,
      "price": 0.37,
      "change": 0.0,
      "premium": -0.32
    },
    {
      "date": "2025-11-14",
      "nav": 0.3711,
      "valuation": 0.2974,
      "price": 0.37,
      "change": -1.33,
      "premium": -0.3
    },
    {
      "date": "2025-11-13",
      "nav": 0.3764,
      "valuation": 0.2974,
      "price": 0.375,
      "change": 0.54,
      "premium": -0.37
    },
    {
      "date": "2025-11-12",
      "nav": 0.3738,
      "valuation": 0.2974,
      "price": 0.373,
      "change": 0.27,
      "premium": -0.21
    },
    {
      "date": "2025-11-11",
      "nav": 0.374,
      "valuation": 0.2974,
      "price": 0.372,
      "change": -0.53,
      "premium": -0.53
    },
    {
      "date": "2025-11-10",
      "nav": 0.3742,
      "valuation": 0.2974,
      "price": 0.374,
      "change": 3.89,
      "premium": -0.05
    },
    {
      "date": "2025-11-07",
      "nav": 0.3584,
      "valuation": 0.2974,
      "price": 0.36,
      "change": 0.0,
      "premium": 0.45
    },
    {
      "date": "2025-11-06",
      "nav": 0.3593,
      "valuation": 0.2974,
      "price": 0.36,
      "change": 0.28,
      "premium": 0.19
    },
    {
      "date": "2025-11-05",
      "nav": 0.3597,
      "valuation": 0.2974,
      "price": 0.359,
      "change": -0.55,
      "premium": -0.19
    },
    {
      "date": "2025-11-04",
      "nav": 0.3613,
      "valuation": 0.2974,
      "price": 0.361,
      "change": -1.1,
      "premium": -0.08
    },
    {
      "date": "2025-11-03",
      "nav": 0.3655,
      "valuation": 0.2974,
      "price": 0.365,
      "change": 0.27,
      "premium": -0.14
    },
    {
      "date": "2025-10-31",
      "nav": 0.3646,
      "valuation": 0.2974,
      "price": 0.364,
      "change": 1.11,
      "premium": -0.16
    },
    {
      "date": "2025-10-30",
      "nav": 0.3598,
      "valuation": 0.2974,
      "price": 0.36,
      "change": 0.0,
      "premium": 0.06
    },
    {
      "date": "2025-10-29",
      "nav": 0.3589,
      "valuation": 0.2974,
      "price": 0.36,
      "change": -0.55,
      "premium": 0.31
    },
    {
      "date": "2025-10-28",
      "nav": 0.3613,
      "valuation": 0.2974,
      "price": 0.362,
      "change": 0.0,
      "premium": 0.19
    },
    {
      "date": "2025-10-27",
      "nav": 0.3611,
      "valuation": 0.2974,
      "price": 0.362,
      "change": 0.0,
      "premium": 0.25
    },
    {
      "date": "2025-10-24",
      "nav": 0.3612,
      "valuation": 0.2974,
      "price": 0.362,
      "change": -1.09,
      "premium": 0.22
    },
    {
      "date": "2025-10-23",
      "nav": 0.3678,
      "valuation": 0.2974,
      "price": 0.366,
      "change": 0.27,
      "premium": -0.49
    },
    {
      "date": "2025-10-22",
      "nav": 0.3656,
      "valuation": 0.2974,
      "price": 0.365,
      "change": -0.27,
      "premium": -0.16
    },
    {
      "date": "2025-10-21",
      "nav": 0.3669,
      "valuation": 0.2974,
      "price": 0.366,
      "change": 0.0,
      "premium": -0.25
    },
    {
      "date": "2025-10-20",
      "nav": 0.3673,
      "valuation": 0.2974,
      "price": 0.366,
      "change": -0.54,
      "premium": -0.35
    },
    {
      "date": "2025-10-17",
      "nav": 0.3691,
      "valuation": 0.2974,
      "price": 0.368,
      "change": -1.34,
      "premium": -0.3
    },
    {
      "date": "2025-10-16",
      "nav": 0.3747,
      "valuation": 0.2974,
      "price": 0.373,
      "change": 1.08,
      "premium": -0.45
    },
    {
      "date": "2025-10-15",
      "nav": 0.3704,
      "valuation": 0.2974,
      "price": 0.369,
      "change": 0.82,
      "premium": -0.38
    },
    {
      "date": "2025-10-14",
      "nav": 0.3676,
      "valuation": 0.2974,
      "price": 0.366,
      "change": 1.39,
      "premium": -0.44
    },
    {
      "date": "2025-10-13",
      "nav": 0.3585,
      "valuation": 0.2974,
      "price": 0.361,
      "change": -0.55,
      "premium": 0.7
    },
    {
      "date": "2025-10-10",
      "nav": 0.3619,
      "valuation": 0.2974,
      "price": 0.363,
      "change": -0.27,
      "premium": 0.3
    },
    {
      "date": "2025-10-09",
      "nav": 0.3627,
      "valuation": 0.2974,
      "price": 0.364,
      "change": -0.82,
      "premium": 0.36
    },
    {
      "date": "2025-09-30",
      "nav": 0.3661,
      "valuation": 0.2974,
      "price": 0.367,
      "change": -0.54,
      "premium": 0.25
    },
    {
      "date": "2025-09-29",
      "nav": 0.3689,
      "valuation": 0.2974,
      "price": 0.369,
      "change": 1.1,
      "premium": 0.03
    },
    {
      "date": "2025-09-26",
      "nav": 0.3631,
      "valuation": 0.2974,
      "price": 0.365,
      "change": -0.54,
      "premium": 0.52
    },
    {
      "date": "2025-09-25",
      "nav": 0.365,
      "valuation": 0.2974,
      "price": 0.367,
      "change": -0.54,
      "premium": 0.55
    },
    {
      "date": "2025-09-24",
      "nav": 0.3683,
      "valuation": 0.2974,
      "price": 0.369,
      "change": 0.0,
      "premium": 0.19
    },
    {
      "date": "2025-09-23",
      "nav": 0.3679,
      "valuation": 0.2974,
      "price": 0.369,
      "change": -0.54,
      "premium": 0.3
    },
    {
      "date": "2025-09-22",
      "nav": 0.3704,
      "valuation": 0.2974,
      "price": 0.371,
      "change": -1.59,
      "premium": 0.16
    },
    {
      "date": "2025-09-19",
      "nav": 0.3753,
      "valuation": 0.2974,
      "price": 0.377,
      "change": 0.8,
      "premium": 0.45
    },
    {
      "date": "2025-09-18",
      "nav": 0.3742,
      "valuation": 0.2974,
      "price": 0.374,
      "change": -1.84,
      "premium": -0.05
    },
    {
      "date": "2025-09-17",
      "nav": 0.3807,
      "valuation": 0.2974,
      "price": 0.381,
      "change": -0.78,
      "premium": 0.08
    },
    {
      "date": "2025-09-16",
      "nav": 0.3838,
      "valuation": 0.2974,
      "price": 0.384,
      "change": 0.0,
      "premium": 0.05
    },
    {
      "date": "2025-09-15",
      "nav": 0.3837,
      "valuation": 0.2974,
      "price": 0.384,
      "change": 0.0,
      "premium": 0.08
    },
    {
      "date": "2025-09-12",
      "nav": 0.3847,
      "valuation": 0.2974,
      "price": 0.384,
      "change": -0.78,
      "premium": -0.18
    },
    {
      "date": "2025-09-11",
      "nav": 0.389,
      "valuation": 0.2974,
      "price": 0.387,
      "change": 0.26,
      "premium": -0.51
    },
    {
      "date": "2025-09-10",
      "nav": 0.3865,
      "valuation": 0.2974,
      "price": 0.386,
      "change": 0.0,
      "premium": -0.13
    },
    {
      "date": "2025-09-09",
      "nav": 0.3868,
      "valuation": 0.2974,
      "price": 0.386,
      "change": 0.0,
      "premium": -0.21
    },
    {
      "date": "2025-09-08",
      "nav": 0.3868,
      "valuation": 0.2974,
      "price": 0.386,
      "change": 1.31,
      "premium": -0.21
    },
    {
      "date": "2025-09-05",
      "nav": 0.3811,
      "valuation": 0.2974,
      "price": 0.381,
      "change": 1.06,
      "premium": -0.03
    },
    {
      "date": "2025-09-04",
      "nav": 0.3787,
      "valuation": 0.2974,
      "price": 0.377,
      "change": -0.53,
      "premium": -0.45
    },
    {
      "date": "2025-09-03",
      "nav": 0.38,
      "valuation": 0.2974,
      "price": 0.379,
      "change": -1.3,
      "premium": -0.26
    },
    {
      "date": "2025-09-02",
      "nav": 0.3844,
      "valuation": 0.2974,
      "price": 0.384,
      "change": -0.52,
      "premium": -0.1
    },
    {
      "date": "2025-09-01",
      "nav": 0.3855,
      "valuation": 0.2974,
      "price": 0.386,
      "change": 0.0,
      "premium": 0.13
    },
    {
      "date": "2025-08-29",
      "nav": 0.3865,
      "valuation": 0.2974,
      "price": 0.386,
      "change": 2.39,
      "premium": -0.13
    },
    {
      "date": "2025-08-28",
      "nav": 0.3775,
      "valuation": 0.2974,
      "price": 0.377,
      "change": -0.53,
      "premium": -0.13
    },
    {
      "date": "2025-08-27",
      "nav": 0.3795,
      "valuation": 0.2974,
      "price": 0.379,
      "change": -2.32,
      "premium": -0.13
    },
    {
      "date": "2025-08-26",
      "nav": 0.3913,
      "valuation": 0.2974,
      "price": 0.388,
      "change": -0.26,
      "premium": -0.84
    },
    {
      "date": "2025-08-25",
      "nav": 0.3904,
      "valuation": 0.2974,
      "price": 0.389,
      "change": 3.73,
      "premium": -0.36
    },
    {
      "date": "2025-08-22",
      "nav": 0.3765,
      "valuation": 0.2974,
      "price": 0.375,
      "change": 0.54,
      "premium": -0.4
    },
    {
      "date": "2025-08-21",
      "nav": 0.374,
      "valuation": 0.2974,
      "price": 0.373,
      "change": -0.8,
      "premium": -0.27
    },
    {
      "date": "2025-08-20",
      "nav": 0.3769,
      "valuation": 0.2974,
      "price": 0.376,
      "change": 2.17,
      "premium": -0.24
    },
    {
      "date": "2025-08-19",
      "nav": 0.3683,
      "valuation": 0.2974,
      "price": 0.368,
      "change": 1.94,
      "premium": -0.08
    },
    {
      "date": "2025-08-18",
      "nav": 0.362,
      "valuation": 0.2974,
      "price": 0.361,
      "change": 0.28,
      "premium": -0.28
    },
    {
      "date": "2025-08-15",
      "nav": 0.3603,
      "valuation": 0.2974,
      "price": 0.36,
      "change": 0.0,
      "premium": -0.08
    },
    {
      "date": "2025-08-14",
      "nav": 0.3598,
      "valuation": 0.2974,
      "price": 0.36,
      "change": 0.28,
      "premium": 0.06
    },
    {
      "date": "2025-08-13",
      "nav": 0.3603,
      "valuation": 0.2974,
      "price": 0.359,
      "change": -0.28,
      "premium": -0.36
    },
    {
      "date": "2025-08-12",
      "nav": 0.3606,
      "valuation": 0.2974,
      "price": 0.36,
      "change": 0.0,
      "premium": -0.17
    },
    {
      "date": "2025-08-11",
      "nav": 0.3618,
      "valuation": 0.2974,
      "price": 0.36,
      "change": 1.41,
      "premium": -0.5
    },
    {
      "date": "2025-08-08",
      "nav": 0.3551,
      "valuation": 0.2974,
      "price": 0.355,
      "change": -0.28,
      "premium": -0.03
    },
    {
      "date": "2025-08-07",
      "nav": 0.3569,
      "valuation": 0.2974,
      "price": 0.356,
      "change": 0.28,
      "premium": -0.25
    },
    {
      "date": "2025-08-06",
      "nav": 0.3563,
      "valuation": 0.2974,
      "price": 0.355,
      "change": 0.0,
      "premium": -0.36
    },
    {
      "date": "2025-08-05",
      "nav": 0.356,
      "valuation": 0.2974,
      "price": 0.355,
      "change": 0.57,
      "premium": -0.28
    },
    {
      "date": "2025-08-04",
      "nav": 0.3521,
      "valuation": 0.2974,
      "price": 0.353,
      "change": 0.28,
      "premium": 0.26
    },
    {
      "date": "2025-08-01",
      "nav": 0.3517,
      "valuation": 0.2974,
      "price": 0.352,
      "change": 0.0,
      "premium": 0.09
    },
    {
      "date": "2025-07-31",
      "nav": 0.3516,
      "valuation": 0.2974,
      "price": 0.352,
      "change": -1.95,
      "premium": 0.11
    },
    {
      "date": "2025-07-30",
      "nav": 0.36,
      "valuation": 0.2974,
      "price": 0.359,
      "change": 0.84,
      "premium": -0.28
    },
    {
      "date": "2025-07-29",
      "nav": 0.3575,
      "valuation": 0.2974,
      "price": 0.356,
      "change": -0.28,
      "premium": -0.42
    },
    {
      "date": "2025-07-28",
      "nav": 0.3584,
      "valuation": 0.2974,
      "price": 0.357,
      "change": -0.28,
      "premium": -0.39
    },
    {
      "date": "2025-07-25",
      "nav": 0.3597,
      "valuation": 0.2974,
      "price": 0.358,
      "change": -1.65,
      "premium": -0.47
    },
    {
      "date": "2025-07-24",
      "nav": 0.366,
      "valuation": 0.2974,
      "price": 0.364,
      "change": 0.55,
      "premium": -0.55
    },
    {
      "date": "2025-07-23",
      "nav": 0.3641,
      "valuation": 0.2974,
      "price": 0.362,
      "change": -0.82,
      "premium": -0.58
    },
    {
      "date": "2025-07-22",
      "nav": 0.3663,
      "valuation": 0.2974,
      "price": 0.365,
      "change": 2.82,
      "premium": -0.35
    },
    {
      "date": "2025-07-21",
      "nav": 0.3563,
      "valuation": 0.2974,
      "price": 0.355,
      "change": 0.28,
      "premium": -0.36
    },
    {
      "date": "2025-07-18",
      "nav": 0.3571,
      "valuation": 0.2974,
      "price": 0.354,
      "change": 0.85,
      "premium": -0.87
    },
    {
      "date": "2025-07-17",
      "nav": 0.3519,
      "valuation": 0.2974,
      "price": 0.351,
      "change": 0.0,
      "premium": -0.26
    },
    {
      "date": "2025-07-16",
      "nav": 0.3513,
      "valuation": 0.2974,
      "price": 0.351,
      "change": 0.57,
      "premium": -0.09
    },
    {
      "date": "2025-07-15",
      "nav": 0.3486,
      "valuation": 0.2974,
      "price": 0.349,
      "change": -0.57,
      "premium": 0.11
    },
    {
      "date": "2025-07-14",
      "nav": 0.3531,
      "valuation": 0.2974,
      "price": 0.351,
      "change": 0.0,
      "premium": -0.59
    },
    {
      "date": "2025-07-11",
      "nav": 0.3524,
      "valuation": 0.2974,
      "price": 0.351,
      "change": 0.57,
      "premium": -0.4
    },
    {
      "date": "2025-07-10",
      "nav": 0.3505,
      "valuation": 0.2974,
      "price": 0.349,
      "change": 0.29,
      "premium": -0.43
    },
    {
      "date": "2025-07-09",
      "nav": 0.3482,
      "valuation": 0.2974,
      "price": 0.348,
      "change": 0.87,
      "premium": -0.06
    },
    {
      "date": "2025-07-08",
      "nav": 0.3465,
      "valuation": 0.2974,
      "price": 0.345,
      "change": 0.58,
      "premium": -0.43
    },
    {
      "date": "2025-07-07",
      "nav": 0.3435,
      "valuation": 0.2974,
      "price": 0.343,
      "change": -0.29,
      "premium": -0.15
    },
    {
      "date": "2025-07-04",
      "nav": 0.3446,
      "valuation": 0.2974,
      "price": 0.344,
      "change": 0.0,
      "premium": -0.17
    },
    {
      "date": "2025-07-03",
      "nav": 0.3444,
      "valuation": 0.2974,
      "price": 0.344,
      "change": 0.29,
      "premium": -0.12
    },
    {
      "date": "2025-07-02",
      "nav": 0.3437,
      "valuation": 0.2974,
      "price": 0.343,
      "change": 0.0,
      "premium": -0.2
    },
    {
      "date": "2025-07-01",
      "nav": 0.3425,
      "valuation": 0.2974,
      "price": 0.343,
      "change": -0.29,
      "premium": 0.15
    },
    {
      "date": "2025-06-30",
      "nav": 0.3444,
      "valuation": 0.2974,
      "price": 0.344,
      "change": 0.58,
      "premium": -0.12
    },
    {
      "date": "2025-06-27",
      "nav": 0.3421,
      "valuation": 0.2974,
      "price": 0.342,
      "change": -0.29,
      "premium": -0.03
    },
    {
      "date": "2025-06-26",
      "nav": 0.3448,
      "valuation": 0.2974,
      "price": 0.343,
      "change": -0.58,
      "premium": -0.52
    },
    {
      "date": "2025-06-25",
      "nav": 0.3449,
      "valuation": 0.2974,
      "price": 0.345,
      "change": 0.29,
      "premium": 0.03
    },
    {
      "date": "2025-06-24",
      "nav": 0.3443,
      "valuation": 0.2974,
      "price": 0.344,
      "change": 0.58,
      "premium": -0.09
    },
    {
      "date": "2025-06-23",
      "nav": 0.3416,
      "valuation": 0.2974,
      "price": 0.342,
      "change": -0.58,
      "premium": 0.12
    },
    {
      "date": "2025-06-20",
      "nav": 0.3457,
      "valuation": 0.2974,
      "price": 0.344,
      "change": 1.18,
      "premium": -0.49
    },
    {
      "date": "2025-06-19",
      "nav": 0.3393,
      "valuation": 0.2974,
      "price": 0.34,
      "change": -0.58,
      "premium": 0.21
    },
    {
      "date": "2025-06-18",
      "nav": 0.3413,
      "valuation": 0.2974,
      "price": 0.342,
      "change": 0.59,
      "premium": 0.21
    },
    {
      "date": "2025-06-17",
      "nav": 0.3392,
      "valuation": 0.2974,
      "price": 0.34,
      "change": 0.0,
      "premium": 0.24
    },
    {
      "date": "2025-06-16",
      "nav": 0.3387,
      "valuation": 0.2974,
      "price": 0.34,
      "change": 0.29,
      "premium": 0.38
    },
    {
      "date": "2025-06-13",
      "nav": 0.3381,
      "valuation": 0.2974,
      "price": 0.339,
      "change": -2.59,
      "premium": 0.27
    },
    {
      "date": "2025-06-12",
      "nav": 0.3471,
      "valuation": 0.2974,
      "price": 0.348,
      "change": -1.69,
      "premium": 0.26
    },
    {
      "date": "2025-06-11",
      "nav": 0.3524,
      "valuation": 0.2974,
      "price": 0.354,
      "change": 0.28,
      "premium": 0.45
    },
    {
      "date": "2025-06-10",
      "nav": 0.3517,
      "valuation": 0.2974,
      "price": 0.353,
      "change": -0.84,
      "premium": 0.37
    },
    {
      "date": "2025-06-09",
      "nav": 0.3549,
      "valuation": 0.2974,
      "price": 0.356,
      "change": -0.28,
      "premium": 0.31
    },
    {
      "date": "2025-06-06",
      "nav": 0.3567,
      "valuation": 0.2974,
      "price": 0.357,
      "change": -0.28,
      "premium": 0.08
    },
    {
      "date": "2025-06-05",
      "nav": 0.3575,
      "valuation": 0.2974,
      "price": 0.358,
      "change": 0.0,
      "premium": 0.14
    },
    {
      "date": "2025-06-04",
      "nav": 0.3573,
      "valuation": 0.2974,
      "price": 0.358,
      "change": 0.28,
      "premium": 0.2
    },
    {
      "date": "2025-06-03",
      "nav": 0.3565,
      "valuation": 0.2974,
      "price": 0.357,
      "change": -0.83,
      "premium": 0.14
    },
    {
      "date": "2025-05-30",
      "nav": 0.3586,
      "valuation": 0.2974,
      "price": 0.36,
      "change": -1.1,
      "premium": 0.39
    },
    {
      "date": "2025-05-29",
      "nav": 0.363,
      "valuation": 0.2974,
      "price": 0.364,
      "change": 0.28,
      "premium": 0.28
    },
    {
      "date": "2025-05-28",
      "nav": 0.363,
      "valuation": 0.2974,
      "price": 0.363,
      "change": 0.0,
      "premium": ""
    },
    {
      "date": "2025-05-27",
      "nav": 0.3619,
      "valuation": 0.2974,
      "price": 0.363,
      "change": 0.28,
      "premium": 0.3
    },
    {
      "date": "2025-05-26",
      "nav": 0.3605,
      "valuation": 0.2974,
      "price": 0.362,
      "change": -0.82,
      "premium": 0.42
    },
    {
      "date": "2025-05-23",
      "nav": 0.3635,
      "valuation": 0.2974,
      "price": 0.365,
      "change": -0.54,
      "premium": 0.41
    },
    {
      "date": "2025-05-22",
      "nav": 0.3659,
      "valuation": 0.2974,
      "price": 0.367,
      "change": -0.54,
      "premium": 0.3
    },
    {
      "date": "2025-05-21",
      "nav": 0.3676,
      "valuation": 0.2974,
      "price": 0.369,
      "change": 0.0,
      "premium": 0.38
    },
    {
      "date": "2025-05-20",
      "nav": 0.3674,
      "valuation": 0.2974,
      "price": 0.369,
      "change": 0.27,
      "premium": 0.44
    },
    {
      "date": "2025-05-19",
      "nav": 0.367,
      "valuation": 0.2974,
      "price": 0.368,
      "change": -1.34,
      "premium": 0.27
    },
    {
      "date": "2025-05-16",
      "nav": 0.3715,
      "valuation": 0.2974,
      "price": 0.373,
      "change": -1.06,
      "premium": 0.4
    },
    {
      "date": "2025-05-15",
      "nav": 0.376,
      "valuation": 0.2974,
      "price": 0.377,
      "change": -0.53,
      "premium": 0.27
    },
    {
      "date": "2025-05-14",
      "nav": 0.3798,
      "valuation": 0.2974,
      "price": 0.379,
      "change": 1.34,
      "premium": -0.21
    },
    {
      "date": "2025-05-13",
      "nav": 0.3738,
      "valuation": 0.2974,
      "price": 0.374,
      "change": 0.0,
      "premium": 0.05
    },
    {
      "date": "2025-05-12",
      "nav": 0.375,
      "valuation": 0.2974,
      "price": 0.374,
      "change": 0.0,
      "premium": -0.27
    },
    {
      "date": "2025-05-09",
      "nav": 0.3734,
      "valuation": 0.2974,
      "price": 0.374,
      "change": 0.0,
      "premium": 0.16
    },
    {
      "date": "2025-05-08",
      "nav": 0.3737,
      "valuation": 0.2974,
      "price": 0.374,
      "change": 0.27,
      "premium": 0.08
    },
    {
      "date": "2025-05-07",
      "nav": 0.3712,
      "valuation": 0.2974,
      "price": 0.373,
      "change": 0.27,
      "premium": 0.48
    },
    {
      "date": "2025-05-06",
      "nav": 0.3702,
      "valuation": 0.2974,
      "price": 0.372,
      "change": 0.54,
      "premium": 0.49
    },
    {
      "date": "2025-04-30",
      "nav": 0.3682,
      "valuation": 0.2974,
      "price": 0.37,
      "change": 0.27,
      "premium": 0.49
    },
    {
      "date": "2025-04-29",
      "nav": 0.3687,
      "valuation": 0.2974,
      "price": 0.369,
      "change": -1.34,
      "premium": 0.08
    },
    {
      "date": "2025-04-28",
      "nav": 0.3735,
      "valuation": 0.2974,
      "price": 0.374,
      "change": -0.27,
      "premium": 0.13
    },
    {
      "date": "2025-04-25",
      "nav": 0.3737,
      "valuation": 0.2974,
      "price": 0.375,
      "change": 0.27,
      "premium": 0.35
    },
    {
      "date": "2025-04-24",
      "nav": 0.3734,
      "valuation": 0.2974,
      "price": 0.374,
      "change": -0.53,
      "premium": 0.16
    },
    {
      "date": "2025-04-23",
      "nav": 0.3753,
      "valuation": 0.2974,
      "price": 0.376,
      "change": -0.27,
      "premium": 0.19
    },
    {
      "date": "2025-04-22",
      "nav": 0.3769,
      "valuation": 0.2974,
      "price": 0.377,
      "change": 0.0,
      "premium": 0.03
    },
    {
      "date": "2025-04-21",
      "nav": 0.3773,
      "valuation": 0.2974,
      "price": 0.377,
      "change": -1.05,
      "premium": -0.08
    },
    {
      "date": "2025-04-18",
      "nav": 0.3814,
      "valuation": 0.2974,
      "price": 0.381,
      "change": -0.52,
      "premium": -0.1
    },
    {
      "date": "2025-04-17",
      "nav": 0.3846,
      "valuation": 0.2974,
      "price": 0.383,
      "change": 0.79,
      "premium": -0.42
    },
    {
      "date": "2025-04-16",
      "nav": 0.3814,
      "valuation": 0.2974,
      "price": 0.38,
      "change": 0.53,
      "premium": -0.37
    },
    {
      "date": "2025-04-15",
      "nav": 0.3804,
      "valuation": 0.2974,
      "price": 0.378,
      "change": -0.53,
      "premium": -0.63
    },
    {
      "date": "2025-04-14",
      "nav": 0.3798,
      "valuation": 0.2974,
      "price": 0.38,
      "change": -0.52,
      "premium": 0.05
    },
    {
      "date": "2025-04-11",
      "nav": 0.3837,
      "valuation": 0.2974,
      "price": 0.382,
      "change": -0.78,
      "premium": -0.44
    },
    {
      "date": "2025-04-10",
      "nav": 0.3879,
      "valuation": 0.2974,
      "price": 0.385,
      "change": 0.52,
      "premium": -0.75
    },
    {
      "date": "2025-04-09",
      "nav": 0.3868,
      "valuation": 0.2974,
      "price": 0.383,
      "change": 1.06,
      "premium": -0.98
    },
    {
      "date": "2025-04-08",
      "nav": 0.3807,
      "valuation": 0.2974,
      "price": 0.379,
      "change": 2.43,
      "premium": -0.45
    },
    {
      "date": "2025-04-07",
      "nav": 0.3712,
      "valuation": 0.2974,
      "price": 0.37,
      "change": -4.15,
      "premium": -0.32
    },
    {
      "date": "2025-04-03",
      "nav": 0.387,
      "valuation": 0.2974,
      "price": 0.386,
      "change": 1.31,
      "premium": -0.26
    },
    {
      "date": "2025-04-02",
      "nav": 0.3817,
      "valuation": 0.2974,
      "price": 0.381,
      "change": 0.26,
      "premium": -0.18
    },
    {
      "date": "2025-04-01",
      "nav": 0.3825,
      "valuation": 0.2974,
      "price": 0.38,
      "change": -0.26,
      "premium": -0.65
    },
    {
      "date": "2025-03-31",
      "nav": 0.3813,
      "valuation": 0.2974,
      "price": 0.381,
      "change": -1.3,
      "premium": -0.08
    },
    {
      "date": "2025-03-28",
      "nav": 0.3865,
      "valuation": 0.2974,
      "price": 0.386,
      "change": -0.77,
      "premium": -0.13
    },
    {
      "date": "2025-03-27",
      "nav": 0.3897,
      "valuation": 0.2974,
      "price": 0.389,
      "change": 1.3,
      "premium": -0.18
    },
    {
      "date": "2025-03-26",
      "nav": 0.386,
      "valuation": 0.2974,
      "price": 0.384,
      "change": -0.26,
      "premium": -0.52
    },
    {
      "date": "2025-03-25",
      "nav": 0.3863,
      "valuation": 0.2974,
      "price": 0.385,
      "change": 0.0,
      "premium": -0.34
    },
    {
      "date": "2025-03-24",
      "nav": 0.3867,
      "valuation": 0.2974,
      "price": 0.385,
      "change": 0.0,
      "premium": -0.44
    },
    {
      "date": "2025-03-21",
      "nav": 0.3863,
      "valuation": 0.2974,
      "price": 0.385,
      "change": -1.28,
      "premium": -0.34
    },
    {
      "date": "2025-03-20",
      "nav": 0.3909,
      "valuation": 0.2974,
      "price": 0.39,
      "change": -1.52,
      "premium": -0.23
    },
    {
      "date": "2025-03-19",
      "nav": 0.398,
      "valuation": 0.2974,
      "price": 0.396,
      "change": -0.75,
      "premium": -0.5
    },
    {
      "date": "2025-03-18",
      "nav": 0.4011,
      "valuation": 0.2974,
      "price": 0.399,
      "change": -0.5,
      "premium": -0.52
    },
    {
      "date": "2025-03-17",
      "nav": 0.4038,
      "valuation": 0.2974,
      "price": 0.401,
      "change": 0.25,
      "premium": -0.69
    },
    {
      "date": "2025-03-14",
      "nav": 0.4039,
      "valuation": 0.2974,
      "price": 0.4,
      "change": 4.17,
      "premium": -0.97
    },
    {
      "date": "2025-03-13",
      "nav": 0.3862,
      "valuation": 0.2974,
      "price": 0.384,
      "change": -0.26,
      "premium": -0.57
    },
    {
      "date": "2025-03-12",
      "nav": 0.3867,
      "valuation": 0.2974,
      "price": 0.385,
      "change": -0.77,
      "premium": -0.44
    },
    {
      "date": "2025-03-11",
      "nav": 0.3905,
      "valuation": 0.2974,
      "price": 0.388,
      "change": 2.37,
      "premium": -0.64
    },
    {
      "date": "2025-03-10",
      "nav": 0.3801,
      "valuation": 0.2974,
      "price": 0.379,
      "change": 0.53,
      "premium": -0.29
    },
    {
      "date": "2025-03-07",
      "nav": 0.3801,
      "valuation": 0.2974,
      "price": 0.377,
      "change": 1.34,
      "premium": -0.82
    },
    {
      "date": "2025-03-06",
      "nav": 0.3736,
      "valuation": 0.2974,
      "price": 0.372,
      "change": 1.36,
      "premium": -0.43
    },
    {
      "date": "2025-03-05",
      "nav": 0.3675,
      "valuation": 0.2974,
      "price": 0.367,
      "change": 0.0,
      "premium": -0.14
    },
    {
      "date": "2025-03-04",
      "nav": 0.3674,
      "valuation": 0.2974,
      "price": 0.367,
      "change": -1.08,
      "premium": -0.11
    },
    {
      "date": "2025-03-03",
      "nav": 0.3713,
      "valuation": 0.2974,
      "price": 0.371,
      "change": -1.07,
      "premium": -0.08
    },
    {
      "date": "2025-02-28",
      "nav": 0.3751,
      "valuation": 0.2974,
      "price": 0.375,
      "change": 0.27,
      "premium": -0.03
    },
    {
      "date": "2025-02-27",
      "nav": 0.3758,
      "valuation": 0.2974,
      "price": 0.374,
      "change": 2.19,
      "premium": -0.48
    },
    {
      "date": "2025-02-26",
      "nav": 0.3675,
      "valuation": 0.2974,
      "price": 0.366,
      "change": 1.1,
      "premium": -0.41
    },
    {
      "date": "2025-02-25",
      "nav": 0.3634,
      "valuation": 0.2974,
      "price": 0.362,
      "change": -1.9,
      "premium": -0.39
    },
    {
      "date": "2025-02-24",
      "nav": 0.37,
      "valuation": 0.2974,
      "price": 0.369,
      "change": 1.1,
      "premium": -0.27
    },
    {
      "date": "2025-02-21",
      "nav": 0.3657,
      "valuation": 0.2974,
      "price": 0.365,
      "change": 0.55,
      "premium": -0.19
    },
    {
      "date": "2025-02-20",
      "nav": 0.3638,
      "valuation": 0.2974,
      "price": 0.363,
      "change": 0.0,
      "premium": -0.22
    },
    {
      "date": "2025-02-19",
      "nav": 0.3648,
      "valuation": 0.2974,
      "price": 0.363,
      "change": 0.55,
      "premium": -0.49
    },
    {
      "date": "2025-02-18",
      "nav": 0.3627,
      "valuation": 0.2974,
      "price": 0.361,
      "change": -1.1,
      "premium": -0.47
    },
    {
      "date": "2025-02-17",
      "nav": 0.3665,
      "valuation": 0.2974,
      "price": 0.365,
      "change": 0.27,
      "premium": -0.41
    },
    {
      "date": "2025-02-14",
      "nav": 0.3654,
      "valuation": 0.2974,
      "price": 0.364,
      "change": 0.0,
      "premium": -0.38
    },
    {
      "date": "2025-02-13",
      "nav": 0.3666,
      "valuation": 0.2974,
      "price": 0.364,
      "change": 2.54,
      "premium": -0.71
    },
    {
      "date": "2025-02-12",
      "nav": 0.3559,
      "valuation": 0.2974,
      "price": 0.355,
      "change": 0.57,
      "premium": -0.25
    },
    {
      "date": "2025-02-11",
      "nav": 0.3513,
      "valuation": 0.2974,
      "price": 0.353,
      "change": -0.84,
      "premium": 0.48
    },
    {
      "date": "2025-02-10",
      "nav": 0.3549,
      "valuation": 0.2974,
      "price": 0.356,
      "change": 0.28,
      "premium": 0.31
    },
    {
      "date": "2025-02-07",
      "nav": 0.3542,
      "valuation": 0.2974,
      "price": 0.355,
      "change": 1.14,
      "premium": 0.23
    },
    {
      "date": "2025-02-06",
      "nav": 0.35,
      "valuation": 0.2974,
      "price": 0.351,
      "change": -0.28,
      "premium": 0.29
    },
    {
      "date": "2025-02-05",
      "nav": 0.3482,
      "valuation": 0.2974,
      "price": 0.352,
      "change": -0.85,
      "premium": 1.09
    },
    {
      "date": "2025-01-27",
      "nav": 0.3544,
      "valuation": 0.2974,
      "price": 0.355,
      "change": -0.28,
      "premium": 0.17
    },
    {
      "date": "2025-01-24",
      "nav": 0.3557,
      "valuation": 0.2974,
      "price": 0.356,
      "change": 0.0,
      "premium": 0.08
    },
    {
      "date": "2025-01-23",
      "nav": 0.3567,
      "valuation": 0.2974,
      "price": 0.356,
      "change": 0.28,
      "premium": -0.2
    },
    {
      "date": "2025-01-22",
      "nav": 0.3561,
      "valuation": 0.2974,
      "price": 0.355,
      "change": -1.93,
      "premium": -0.31
    },
    {
      "date": "2025-01-21",
      "nav": 0.3624,
      "valuation": 0.2974,
      "price": 0.362,
      "change": -0.82,
      "premium": -0.11
    },
    {
      "date": "2025-01-20",
      "nav": 0.3662,
      "valuation": 0.2974,
      "price": 0.365,
      "change": 0.83,
      "premium": -0.33
    },
    {
      "date": "2025-01-17",
      "nav": 0.3628,
      "valuation": 0.2974,
      "price": 0.362,
      "change": 0.56,
      "premium": -0.22
    },
    {
      "date": "2025-01-16",
      "nav": 0.3602,
      "valuation": 0.2974,
      "price": 0.36,
      "change": -0.28,
      "premium": -0.06
    },
    {
      "date": "2025-01-15",
      "nav": 0.3624,
      "valuation": 0.2974,
      "price": 0.361,
      "change": -0.28,
      "premium": -0.39
    },
    {
      "date": "2025-01-14",
      "nav": 0.3638,
      "valuation": 0.2974,
      "price": 0.362,
      "change": 2.26,
      "premium": -0.49
    },
    {
      "date": "2025-01-13",
      "nav": 0.3545,
      "valuation": 0.2974,
      "price": 0.354,
      "change": 0.57,
      "premium": -0.14
    },
    {
      "date": "2025-01-10",
      "nav": 0.3514,
      "valuation": 0.2974,
      "price": 0.352,
      "change": -1.68,
      "premium": 0.17
    },
    {
      "date": "2025-01-09",
      "nav": 0.3576,
      "valuation": 0.2974,
      "price": 0.358,
      "change": 0.0,
      "premium": 0.11
    },
    {
      "date": "2025-01-08",
      "nav": 0.3567,
      "valuation": 0.2974,
      "price": 0.358,
      "change": -0.56,
      "premium": 0.36
    },
    {
      "date": "2025-01-07",
      "nav": 0.3585,
      "valuation": 0.2974,
      "price": 0.36,
      "change": 0.56,
      "premium": 0.42
    },
    {
      "date": "2025-01-06",
      "nav": 0.3571,
      "valuation": 0.2974,
      "price": 0.358,
      "change": -2.98,
      "premium": 0.25
    },
    {
      "date": "2025-01-03",
      "nav": 0.3669,
      "valuation": 0.2974,
      "price": 0.369,
      "change": -0.81,
      "premium": 0.57
    },
    {
      "date": "2025-01-02",
      "nav": 0.3716,
      "valuation": 0.2974,
      "price": 0.372,
      "change": -2.36,
      "premium": 0.11
    },
    {
      "date": "2024-12-31",
      "nav": 0.3811,
      "valuation": 0.2974,
      "price": 0.381,
      "change": -0.52,
      "premium": -0.03
    },
    {
      "date": "2024-12-30",
      "nav": 0.3818,
      "valuation": 0.2974,
      "price": 0.383,
      "change": -0.78,
      "premium": 0.31
    },
    {
      "date": "2024-12-27",
      "nav": 0.3851,
      "valuation": 0.2974,
      "price": 0.386,
      "change": 0.26,
      "premium": 0.23
    },
    {
      "date": "2024-12-26",
      "nav": 0.3845,
      "valuation": 0.2974,
      "price": 0.385,
      "change": 0.26,
      "premium": 0.13
    },
    {
      "date": "2024-12-25",
      "nav": 0.3846,
      "valuation": 0.2974,
      "price": 0.384,
      "change": -0.52,
      "premium": -0.16
    },
    {
      "date": "2024-12-24",
      "nav": 0.3865,
      "valuation": 0.2974,
      "price": 0.386,
      "change": 0.78,
      "premium": -0.13
    },
    {
      "date": "2024-12-23",
      "nav": 0.3832,
      "valuation": 0.2974,
      "price": 0.383,
      "change": -1.03,
      "premium": -0.05
    },
    {
      "date": "2024-12-20",
      "nav": 0.3876,
      "valuation": 0.2974,
      "price": 0.387,
      "change": 0.26,
      "premium": -0.15
    },
    {
      "date": "2024-12-19",
      "nav": 0.3865,
      "valuation": 0.2974,
      "price": 0.386,
      "change": -1.28,
      "premium": -0.13
    },
    {
      "date": "2024-12-18",
      "nav": 0.3924,
      "valuation": 0.2974,
      "price": 0.391,
      "change": -0.51,
      "premium": -0.36
    },
    {
      "date": "2024-12-17",
      "nav": 0.3937,
      "valuation": 0.2974,
      "price": 0.393,
      "change": 0.26,
      "premium": -0.18
    },
    {
      "date": "2024-12-16",
      "nav": 0.3933,
      "valuation": 0.2974,
      "price": 0.392,
      "change": -2.0,
      "premium": -0.33
    },
    {
      "date": "2024-12-13",
      "nav": 0.4008,
      "valuation": 0.2974,
      "price": 0.4,
      "change": -2.44,
      "premium": -0.2
    },
    {
      "date": "2024-12-12",
      "nav": 0.4135,
      "valuation": 0.2974,
      "price": 0.41,
      "change": 1.74,
      "premium": -0.85
    },
    {
      "date": "2024-12-11",
      "nav": 0.404,
      "valuation": 0.2974,
      "price": 0.403,
      "change": 1.0,
      "premium": -0.25
    },
    {
      "date": "2024-12-10",
      "nav": 0.4007,
      "valuation": 0.2974,
      "price": 0.399,
      "change": 1.01,
      "premium": -0.42
    },
    {
      "date": "2024-12-09",
      "nav": 0.3934,
      "valuation": 0.2974,
      "price": 0.395,
      "change": 0.25,
      "premium": 0.41
    },
    {
      "date": "2024-12-06",
      "nav": 0.3939,
      "valuation": 0.2974,
      "price": 0.394,
      "change": 0.77,
      "premium": 0.03
    },
    {
      "date": "2024-12-05",
      "nav": 0.391,
      "valuation": 0.2974,
      "price": 0.391,
      "change": -0.26,
      "premium": ""
    },
    {
      "date": "2024-12-04",
      "nav": 0.3922,
      "valuation": 0.2974,
      "price": 0.392,
      "change": -0.76,
      "premium": -0.05
    },
    {
      "date": "2024-12-03",
      "nav": 0.3959,
      "valuation": 0.2974,
      "price": 0.395,
      "change": -0.25,
      "premium": -0.23
    },
    {
      "date": "2024-12-02",
      "nav": 0.3971,
      "valuation": 0.2974,
      "price": 0.396,
      "change": 0.25,
      "premium": -0.28
    },
    {
      "date": "2024-11-29",
      "nav": 0.3953,
      "valuation": 0.2974,
      "price": 0.395,
      "change": 1.54,
      "premium": -0.08
    },
    {
      "date": "2024-11-28",
      "nav": 0.3898,
      "valuation": 0.2974,
      "price": 0.389,
      "change": -0.77,
      "premium": -0.21
    },
    {
      "date": "2024-11-27",
      "nav": 0.3936,
      "valuation": 0.2974,
      "price": 0.392,
      "change": 1.03,
      "premium": -0.41
    },
    {
      "date": "2024-11-26",
      "nav": 0.3878,
      "valuation": 0.2974,
      "price": 0.388,
      "change": 1.04,
      "premium": 0.05
    },
    {
      "date": "2024-11-25",
      "nav": 0.3853,
      "valuation": 0.2974,
      "price": 0.384,
      "change": -0.78,
      "premium": -0.34
    },
    {
      "date": "2024-11-22",
      "nav": 0.3849,
      "valuation": 0.2974,
      "price": 0.387,
      "change": -3.01,
      "premium": 0.55
    },
    {
      "date": "2024-11-21",
      "nav": 0.3985,
      "valuation": 0.2974,
      "price": 0.399,
      "change": 0.0,
      "premium": 0.13
    },
    {
      "date": "2024-11-20",
      "nav": 0.3997,
      "valuation": 0.2974,
      "price": 0.399,
      "change": 0.25,
      "premium": -0.18
    },
    {
      "date": "2024-11-19",
      "nav": 0.3973,
      "valuation": 0.2974,
      "price": 0.398,
      "change": 0.0,
      "premium": 0.18
    },
    {
      "date": "2024-11-18",
      "nav": 0.3984,
      "valuation": 0.2974,
      "price": 0.398,
      "change": -1.24,
      "premium": -0.1
    },
    {
      "date": "2024-11-15",
      "nav": 0.4042,
      "valuation": 0.2974,
      "price": 0.403,
      "change": -1.23,
      "premium": -0.3
    },
    {
      "date": "2024-11-14",
      "nav": 0.4087,
      "valuation": 0.2974,
      "price": 0.408,
      "change": -1.21,
      "premium": -0.17
    },
    {
      "date": "2024-11-13",
      "nav": 0.414,
      "valuation": 0.2974,
      "price": 0.413,
      "change": 0.0,
      "premium": -0.24
    },
    {
      "date": "2024-11-12",
      "nav": 0.414,
      "valuation": 0.2974,
      "price": 0.413,
      "change": -0.48,
      "premium": -0.24
    },
    {
      "date": "2024-11-11",
      "nav": 0.417,
      "valuation": 0.2974,
      "price": 0.415,
      "change": -0.48,
      "premium": -0.48
    },
    {
      "date": "2024-11-08",
      "nav": 0.4191,
      "valuation": 0.2974,
      "price": 0.417,
      "change": -2.11,
      "premium": -0.5
    },
    {
      "date": "2024-11-07",
      "nav": 0.4289,
      "valuation": 0.2974,
      "price": 0.426,
      "change": 7.3,
      "premium": -0.68
    },
    {
      "date": "2024-11-06",
      "nav": 0.3986,
      "valuation": 0.2974,
      "price": 0.397,
      "change": 0.0,
      "premium": -0.4
    },
    {
      "date": "2024-11-05",
      "nav": 0.4,
      "valuation": 0.2974,
      "price": 0.397,
      "change": 2.32,
      "premium": -0.75
    },
    {
      "date": "2024-11-04",
      "nav": 0.3907,
      "valuation": 0.2974,
      "price": 0.388,
      "change": 0,
      "premium": -0.69
    }
  ]
}